{ 
  "name": "ultimaFabula",
  "title": "ultimaFabula",
  "description": "The non-official Fabula Ultima system for FoundryVTT!",
  "version": "1.0.0",
  "minimumCoreVersion": "0.8.6",
  "compatibility": {
    "minimum": "10",
    "maximum": "11"
  },
  "author": "Cqn",
  "esmodules": ["module/ultimaFabula.mjs"],
  "styles": ["css/ultimaFabula.css"],
  "scripts": [],
  "packs": [],
  "languages": [
    {
      "lang": "en",
      "name": "English",
      "path": "lang/en.json"
    }
  ],
  "gridDistance": 1.5,
  "gridUnits": "m",
  "primaryTokenAttribute": "resources.hp",
  "secondaryTokenAttribute": "resources.mp",
  "url": "",
  "manifest": "",
  "download": "",
  "license": "LICENSE.txt"
}
